{
  "runner_version": "w3_fixed_lqr_survival_replay_v2_chunked",
  "status": "complete",
  "run_id": 13,
  "chunk_index": 8,
  "chunk_count": 64,
  "row_start": 6400,
  "row_stop": 7200,
  "row_count": 800,
  "storage_format": "csv_gz",
  "compression_level": 1,
  "partition_path": "w3_survival_rows/c00008.csv.gz",
  "byte_count": 1532916,
  "checksum_sha256": "7caadae6dd01ed02907a4b350079db92fe065fd86575e57b971c5dd8c902e5b3",
  "duration_s": 158.53355240821838,
  "table_name": "w3_survival_rows"
}
