{
  "runner_version": "run_lqr_w01_dense_chunked_v1",
  "status": "complete",
  "run_id": 15,
  "chunk_index": 23,
  "chunk_count": 96,
  "row_start": 18400,
  "row_stop": 19200,
  "row_count": 800,
  "storage_format": "csv_gz",
  "compression_level": 1,
  "partition_path": "w01_primitive_rows/c00023.csv.gz",
  "byte_count": 1040473,
  "checksum_sha256": "838f2262dfc71c7b423e483148fcdbbb047ae10618fad200a087b5c31bc2faa1",
  "duration_s": 14.156257152557373,
  "table_name": "w01_primitive_rows"
}
