{
  "config": {
    "actuator_tau_s": [
      0.05049432643111373,
      0.05049432643111373,
      0.05049432643111373
    ],
    "dynamics_defect_tolerance": 0.0005,
    "energy_loss_weight": 0.02,
    "heading_weight": 20.0,
    "ipopt_max_iter": 220,
    "max_alpha_deg": 28.0,
    "max_bank_deg": 85.0,
    "max_beta_deg": 35.0,
    "max_pitch_deg": 65.0,
    "max_solver_time_s": 30.0,
    "min_wall_margin_m": 0.0,
    "n_intervals": 18,
    "recovery_weight": 34.0,
    "rho_kg_m3": 1.225,
    "saturation_weight": 0.12,
    "slack_weight": 100000.0,
    "smoothness_weight": 0.3,
    "solver_name": "casadi_ipopt",
    "speed_bounds_m_s": [
      2.5,
      9.5
    ],
    "t_max_s": 1.25,
    "t_min_s": 1.03,
    "terminal_alpha_deg": 7.0,
    "terminal_alpha_weight": 28.0,
    "terminal_altitude_min_m": 0.75,
    "terminal_bank_deg": 20.0,
    "terminal_beta_deg": 15.0,
    "terminal_beta_weight": 14.0,
    "terminal_pitch_deg": 15.0,
    "terminal_rate_max_rad_s": 0.7,
    "terminal_rate_weight": 6.0,
    "terminal_speed_bounds_m_s": [
      5.8,
      7.0
    ],
    "terminal_speed_target_m_s": 6.4,
    "terminal_speed_weight": 7.0,
    "terminal_wall_margin_m": 0.1
  },
  "failure_reason": "solver_failure: Error in Opti::solve [OptiNode] at .../casadi/core/optistack.cpp:217:\n.../casadi/core/optistack_internal.cpp:1338: Assertion \"return_success(accept_limit)\" failed:\nSolver failed. You may use opti.debug.value to investigate the latest values of variables. return_status is 'Maximum_Iterations_Exceeded'",
  "feasibility_label": "solver_failure",
  "has_tvlqr": false,
  "metrics": {
    "actual_heading_change_deg": -61.96835525928054,
    "allow_high_alpha": false,
    "allow_safety_slack": false,
    "command_norm_max_abs": 1.0,
    "directed_heading_change_deg": -1378.0316447407195,
    "direction": "left",
    "duration_s": 1.03,
    "dynamics_defect_max": 0.0,
    "exit_recoverable_gate": false,
    "heading_gate_passed": true,
    "heading_threshold_deg": 24.0,
    "inside_true_safety_volume": false,
    "max_abs_phi_deg": 1597.4424018009315,
    "max_abs_rate_rad_s": 6.390908223667447,
    "max_abs_theta_deg": 169.54323068100635,
    "max_alpha_deg": 43.954039123773654,
    "max_beta_deg": 47.9708267108388,
    "min_ceiling_margin_m": 0.2999999999999998,
    "min_floor_margin_m": -1.4525469912395716,
    "min_wall_distance_m": 0.25,
    "objective_value": Infinity,
    "sample_count": 19,
    "saturation_fraction": 0.37037037037037035,
    "slack_max": 0.0,
    "slack_nonzero": false,
    "target_heading_deg": 30.0,
    "terminal_abs_alpha_deg": 43.954039123773654,
    "terminal_abs_beta_deg": 7.822964774564447,
    "terminal_abs_phi_deg": 1232.0320163381389,
    "terminal_abs_theta_deg": 169.54323068100635,
    "terminal_rate_norm_rad_s": 5.028778419755687,
    "terminal_speed_m_s": 5.2338062481441225,
    "terminal_z_w_m": -1.4525469912395716,
    "unwrapped_heading_change_deg": 1378.0316447407195,
    "wind_case": "w0"
  },
  "solver_stats": {
    "candidate_variant": "latency105",
    "exception": "Error in Opti::solve [OptiNode] at .../casadi/core/optistack.cpp:217:\n.../casadi/core/optistack_internal.cpp:1338: Assertion \"return_success(accept_limit)\" failed:\nSolver failed. You may use opti.debug.value to investigate the latest values of variables. return_status is 'Maximum_Iterations_Exceeded'",
    "initial_guess_name": "template_seed",
    "return_status": "solver_exception",
    "solver_name": "casadi_ipopt"
  },
  "success": false,
  "target": {
    "allow_high_alpha": false,
    "allow_safety_slack": false,
    "direction": "left",
    "target_heading_deg": 30.0,
    "wind_case": "w0"
  },
  "trajectory_npz": "03_Control/05_Results/03_primitives/11_tight_turn_phase2_latency_recovery/001/trajectories/ocp030_hard_latency105_hard_template_s001.npz"
}
