{
  "runner_version": "run_lqr_w01_dense_chunked_v53",
  "status": "complete",
  "run_id": 32,
  "chunk_index": 13,
  "chunk_count": 168,
  "row_start": 10400,
  "row_stop": 11200,
  "row_count": 800,
  "storage_format": "csv_gz",
  "compression_level": 1,
  "partition_path": "w01_primitive_rows/c00013.csv.gz",
  "byte_count": 1553940,
  "checksum_sha256": "c212c50860b7b5a4f14bd21ce80ecf5cb559582b966b3c415941c4cfe18f55c6",
  "duration_s": 41.68936228752136,
  "table_name": "w01_primitive_rows",
  "primitive_timing_contract": {
    "finite_horizon_s": 0.1,
    "controller_input_slots_per_primitive": 5,
    "controller_input_update_period_s": 0.02,
    "primitive_timing_contract_version": "v411_0p10s_5slot_20ms"
  }
}
