{
  "runner_version": "run_lqr_w01_dense_chunked_v524",
  "status": "complete",
  "run_id": 2,
  "chunk_index": 8,
  "chunk_count": 128,
  "row_start": 6400,
  "row_stop": 7200,
  "row_count": 800,
  "storage_format": "csv_gz",
  "compression_level": 1,
  "partition_path": "w01_primitive_rows/c00008.csv.gz",
  "byte_count": 2061255,
  "checksum_sha256": "d6d355a857c79aacc9d6edbeac0970a0d55b874e2aa5d04b5bde71b40a2db1ea",
  "duration_s": 98.71230006217957,
  "table_name": "w01_primitive_rows",
  "primitive_timing_contract": {
    "finite_horizon_s": 0.1,
    "controller_input_slots_per_primitive": 5,
    "controller_input_update_period_s": 0.02,
    "primitive_timing_contract_version": "v411_0p10s_5slot_20ms"
  }
}
