{
  "runner_version": "run_lqr_w01_dense_chunked_v524",
  "status": "complete",
  "run_id": 906,
  "chunk_index": 99,
  "chunk_count": 128,
  "row_start": 79200,
  "row_stop": 80000,
  "row_count": 800,
  "storage_format": "csv_gz",
  "compression_level": 1,
  "partition_path": "w01_primitive_rows/c00099.csv.gz",
  "byte_count": 2018085,
  "checksum_sha256": "f5caedfbe945731d2ef668e45144e52b2b40005a2d9e81cc269f0a921aae25bb",
  "duration_s": 81.68712735176086,
  "table_name": "w01_primitive_rows",
  "primitive_timing_contract": {
    "finite_horizon_s": 0.1,
    "controller_input_slots_per_primitive": 5,
    "controller_input_update_period_s": 0.02,
    "primitive_timing_contract_version": "v411_0p10s_5slot_20ms"
  }
}
