{
  "runner_version": "run_lqr_w01_dense_chunked_v524",
  "status": "complete",
  "run_id": 906,
  "chunk_index": 86,
  "chunk_count": 128,
  "row_start": 68800,
  "row_stop": 69600,
  "row_count": 800,
  "storage_format": "csv_gz",
  "compression_level": 1,
  "partition_path": "w01_primitive_rows/c00086.csv.gz",
  "byte_count": 2060238,
  "checksum_sha256": "458d45fc957996a66dae9c2e8c84b1cb16f616306fc34e80e889076903fd74ee",
  "duration_s": 97.34792494773865,
  "table_name": "w01_primitive_rows",
  "primitive_timing_contract": {
    "finite_horizon_s": 0.1,
    "controller_input_slots_per_primitive": 5,
    "controller_input_update_period_s": 0.02,
    "primitive_timing_contract_version": "v411_0p10s_5slot_20ms"
  }
}
