{
  "runner_version": "w2_fixed_lqr_survival_replay_v411",
  "status": "complete",
  "run_id": 16,
  "chunk_index": 45,
  "chunk_count": 64,
  "row_start": 36000,
  "row_stop": 36800,
  "row_count": 800,
  "storage_format": "csv_gz",
  "compression_level": 1,
  "partition_path": "w2_survival_rows/c00045.csv.gz",
  "byte_count": 1174119,
  "checksum_sha256": "181b9887a0fbf8b643b16649b8e16f2e530d3625828c88c2d945a7f2c1412f67",
  "duration_s": 38.96090316772461,
  "table_name": "w2_survival_rows",
  "primitive_timing_contract": {
    "finite_horizon_s": 0.1,
    "controller_input_slots_per_primitive": 5,
    "controller_input_update_period_s": 0.02,
    "primitive_timing_contract_version": "v411_0p10s_5slot_20ms"
  }
}
