{
  "runner_version": "r7_fixed_lqr_survival_replay_v415_includes_dry_air",
  "status": "complete",
  "run_id": 21,
  "chunk_index": 107,
  "chunk_count": 374,
  "row_start": 85600,
  "row_stop": 86400,
  "row_count": 800,
  "storage_format": "csv_gz",
  "compression_level": 1,
  "partition_path": "w3_survival_rows/c00107.csv.gz",
  "byte_count": 1963364,
  "checksum_sha256": "1be5a24947972b0ceb6dbe006be2ed726ae8d24536602ddc412dadf51ccff707",
  "duration_s": 106.69964218139648,
  "table_name": "w3_survival_rows",
  "primitive_timing_contract": {
    "finite_horizon_s": 0.1,
    "controller_input_slots_per_primitive": 5,
    "controller_input_update_period_s": 0.02,
    "primitive_timing_contract_version": "v411_0p10s_5slot_20ms"
  }
}
