{
  "runner_version": "r7_fixed_lqr_survival_replay_v415_includes_dry_air",
  "status": "complete",
  "run_id": 21,
  "chunk_index": 106,
  "chunk_count": 374,
  "row_start": 84800,
  "row_stop": 85600,
  "row_count": 800,
  "storage_format": "csv_gz",
  "compression_level": 1,
  "partition_path": "w3_survival_rows/c00106.csv.gz",
  "byte_count": 1920739,
  "checksum_sha256": "5213df495a335c879024bd9c2168c798b89dce7e60e69247862ccc2c04b7d9ae",
  "duration_s": 26.62234878540039,
  "table_name": "w3_survival_rows",
  "primitive_timing_contract": {
    "finite_horizon_s": 0.1,
    "controller_input_slots_per_primitive": 5,
    "controller_input_update_period_s": 0.02,
    "primitive_timing_contract_version": "v411_0p10s_5slot_20ms"
  }
}
