{
  "runner_version": "r7_fixed_lqr_survival_replay_v415_includes_dry_air",
  "status": "complete",
  "run_id": 21,
  "chunk_index": 190,
  "chunk_count": 374,
  "row_start": 152000,
  "row_stop": 152800,
  "row_count": 800,
  "storage_format": "csv_gz",
  "compression_level": 1,
  "partition_path": "w3_survival_rows/c00190.csv.gz",
  "byte_count": 1829824,
  "checksum_sha256": "398c2cb483a0da1957f0fad41af2080315fba9c937f909b6191cae8aa07ae9fa",
  "duration_s": 50.173481702804565,
  "table_name": "w3_survival_rows",
  "primitive_timing_contract": {
    "finite_horizon_s": 0.1,
    "controller_input_slots_per_primitive": 5,
    "controller_input_update_period_s": 0.02,
    "primitive_timing_contract_version": "v411_0p10s_5slot_20ms"
  }
}
