{
  "runner_version": "r7_fixed_lqr_survival_replay_v415_includes_dry_air",
  "status": "complete",
  "run_id": 21,
  "chunk_index": 250,
  "chunk_count": 374,
  "row_start": 200000,
  "row_stop": 200800,
  "row_count": 800,
  "storage_format": "csv_gz",
  "compression_level": 1,
  "partition_path": "w3_survival_rows/c00250.csv.gz",
  "byte_count": 1950961,
  "checksum_sha256": "17a7cde68594a78d71360f5e78fd221e85d0e604d1d99f8f819f120034a9e515",
  "duration_s": 57.61290144920349,
  "table_name": "w3_survival_rows",
  "primitive_timing_contract": {
    "finite_horizon_s": 0.1,
    "controller_input_slots_per_primitive": 5,
    "controller_input_update_period_s": 0.02,
    "primitive_timing_contract_version": "v411_0p10s_5slot_20ms"
  }
}
