{
  "runner_version": "run_lqr_w01_dense_chunked_v53",
  "status": "complete",
  "run_id": 33,
  "chunk_index": 2,
  "chunk_count": 135,
  "row_start": 2000,
  "row_stop": 3000,
  "row_count": 1000,
  "storage_format": "csv_gz",
  "compression_level": 1,
  "partition_path": "w01_primitive_rows/c00002.csv.gz",
  "byte_count": 2092160,
  "checksum_sha256": "342f17abaacc5e96632f14b9f712832d805ace5e2d25acf3d59d619be85e039b",
  "duration_s": 87.99761438369751,
  "table_name": "w01_primitive_rows",
  "primitive_timing_contract": {
    "finite_horizon_s": 0.1,
    "controller_input_slots_per_primitive": 5,
    "controller_input_update_period_s": 0.02,
    "primitive_timing_contract_version": "v411_0p10s_5slot_20ms"
  }
}
