{
  "runner_version": "run_lqr_w01_dense_chunked_v53",
  "status": "complete",
  "run_id": 36,
  "chunk_index": 56,
  "chunk_count": 168,
  "row_start": 44800,
  "row_stop": 45600,
  "row_count": 800,
  "storage_format": "csv_gz",
  "compression_level": 1,
  "partition_path": "w01_primitive_rows/c00056.csv.gz",
  "byte_count": 1692112,
  "checksum_sha256": "6a4e8929721af4a1d3d6838f496100f9b1c4cea727b492b7153ff4ab8a144e0f",
  "duration_s": 54.184606313705444,
  "table_name": "w01_primitive_rows",
  "primitive_timing_contract": {
    "finite_horizon_s": 0.1,
    "controller_input_slots_per_primitive": 5,
    "controller_input_update_period_s": 0.02,
    "primitive_timing_contract_version": "v411_0p10s_5slot_20ms"
  }
}
