{
  "runner_version": "run_lqr_w01_dense_chunked_v53",
  "status": "complete",
  "run_id": 27,
  "chunk_index": 139,
  "chunk_count": 168,
  "row_start": 111200,
  "row_stop": 112000,
  "row_count": 800,
  "storage_format": "csv_gz",
  "compression_level": 1,
  "partition_path": "w01_primitive_rows/c00139.csv.gz",
  "byte_count": 1506134,
  "checksum_sha256": "6e349d1dd6e77d7d8caae655c3da1559337fe1d931aa18034b6aeec4317a331b",
  "duration_s": 30.98735523223877,
  "table_name": "w01_primitive_rows",
  "primitive_timing_contract": {
    "finite_horizon_s": 0.1,
    "controller_input_slots_per_primitive": 5,
    "controller_input_update_period_s": 0.02,
    "primitive_timing_contract_version": "v411_0p10s_5slot_20ms"
  }
}
